idecomp/__init__.py
idecomp/config.py
idecomp/py.typed
idecomp/decomp/__init__.py
idecomp/decomp/arquivos.py
idecomp/decomp/avl_cortesfpha_dec.py
idecomp/decomp/avl_turb_max.py
idecomp/decomp/caso.py
idecomp/decomp/cortdeco.py
idecomp/decomp/custos.py
idecomp/decomp/dadger.py
idecomp/decomp/dadgnl.py
idecomp/decomp/dec_avl_evap.py
idecomp/decomp/dec_cortes_evap.py
idecomp/decomp/dec_desvfpha.py
idecomp/decomp/dec_eco_cotajus.py
idecomp/decomp/dec_eco_discr.py
idecomp/decomp/dec_eco_evap.py
idecomp/decomp/dec_eco_qlat.py
idecomp/decomp/dec_estatevap.py
idecomp/decomp/dec_estatfpha.py
idecomp/decomp/dec_fcf_cortes.py
idecomp/decomp/dec_oper_evap.py
idecomp/decomp/dec_oper_gnl.py
idecomp/decomp/dec_oper_interc.py
idecomp/decomp/dec_oper_ree.py
idecomp/decomp/dec_oper_rhesoft.py
idecomp/decomp/dec_oper_sist.py
idecomp/decomp/dec_oper_usie.py
idecomp/decomp/dec_oper_usih.py
idecomp/decomp/dec_oper_usit.py
idecomp/decomp/decomptim.py
idecomp/decomp/eco_fpha.py
idecomp/decomp/fcfnw.py
idecomp/decomp/hidr.py
idecomp/decomp/inviabunic.py
idecomp/decomp/mapcut.py
idecomp/decomp/oper_desvio_fpha.py
idecomp/decomp/oper_disp_usih.py
idecomp/decomp/oper_disp_usih_ree.py
idecomp/decomp/oper_disp_usih_subm.py
idecomp/decomp/postos.py
idecomp/decomp/relato.py
idecomp/decomp/relgnl.py
idecomp/decomp/vazoes.py
idecomp/decomp/modelos/__init__.py
idecomp/decomp/modelos/arquivos.py
idecomp/decomp/modelos/avl_cortesfpha_dec.py
idecomp/decomp/modelos/avl_turb_max.py
idecomp/decomp/modelos/caso.py
idecomp/decomp/modelos/cortdeco.py
idecomp/decomp/modelos/custos.py
idecomp/decomp/modelos/dadger.py
idecomp/decomp/modelos/dadgnl.py
idecomp/decomp/modelos/dec_avl_evap.py
idecomp/decomp/modelos/dec_cortes_evap.py
idecomp/decomp/modelos/dec_desvfpha.py
idecomp/decomp/modelos/dec_eco_cotajus.py
idecomp/decomp/modelos/dec_eco_discr.py
idecomp/decomp/modelos/dec_eco_evap.py
idecomp/decomp/modelos/dec_eco_qlat.py
idecomp/decomp/modelos/dec_estatevap.py
idecomp/decomp/modelos/dec_estatfpha.py
idecomp-1.7.3.dist-info/METADATA
idecomp-1.7.3.dist-info/WHEEL
idecomp-1.7.3.dist-info/licenses/LICENSE.md
idecomp-1.7.3.dist-info/RECORD
