Metadata-Version: 2.4
Name: idecomp
Version: 1.7.3
Summary: idecomp
Project-URL: Documentation, https://rjmalves.github.io/idecomp/
Project-URL: Repository, https://github.com/rjmalves/idecomp/
Author-email: Rogerio Alves <rogerioalves.ee@gmail.com>, Mariana Noel <marianasimoesnoel@gmail.com>
License: MIT License
License-File: LICENSE.md
Classifier: Development Status :: 5 - Production/Stable
Classifier: Intended Audience :: Developers
Classifier: License :: OSI Approved :: MIT License
Classifier: Operating System :: OS Independent
Classifier: Programming Language :: Python :: 3.10
Requires-Python: >=3.10
Requires-Dist: cfinterface>=1.8
Requires-Dist: numpy>=2.0
Requires-Dist: pandas>=2.2
Provides-Extra: dev
Requires-Dist: matplotlib; extra == 'dev'
Requires-Dist: mypy; extra == 'dev'
Requires-Dist: numpydoc; extra == 'dev'
Requires-Dist: plotly; extra == 'dev'
Requires-Dist: pytest; extra == 'dev'
Requires-Dist: pytest-cov; extra == 'dev'
Requires-Dist: ruff; extra == 'dev'
Requires-Dist: sphinx; extra == 'dev'
Requires-Dist: sphinx-gallery; extra == 'dev'
Requires-Dist: sphinx-rtd-theme; extra == 'dev'
